<?xml version="1.0" encoding="UTF-8" standalone="yes"?>
<Ingredients>
	<Ingredient qty="225.000" uom="g" recipe="P-18907" invFactor="0.1837" conversion="0.00100000" ingredient="I-3643"/>
	<Ingredient qty="1000.000" uom="g" recipe="P-18907" invFactor="0.8163" conversion="1.00000000" ingredient="I-6026"/>
	<Ingredient qty="2.270" uom="Kg" recipe="P-19175" invFactor="1.4188" conversion="2.20462000" ingredient="I-6807"/>
	<Ingredient qty="10.000" uom="Kg" recipe="P-20239" invFactor="1.3514" conversion="4.00000000" ingredient="I-4698"/>
	<Ingredient qty="1.000" uom="lb" recipe="P-24452" invFactor="1.1111" conversion="1.00000000" ingredient="I-4381"/>
	<Ingredient qty="1.000" uom="Kg" recipe="P-25993" invFactor="0.0002" conversion="1000.00000000" ingredient="I-3642"/>
	<Ingredient qty="5.000" uom="Kg" recipe="P-25993" invFactor="0.0008" conversion="1000.00000000" ingredient="I-6026"/>
	<Ingredient qty="225.000" uom="g" recipe="P-26019" invFactor="0.1837" conversion="0.00100000" ingredient="I-3643"/>
	<Ingredient qty="1000.000" uom="g" recipe="P-26019" invFactor="0.8163" conversion="1.00000000" ingredient="I-6026"/>
	<Ingredient qty="750.000" uom="ml" recipe="P-26020" invFactor="300.0000" conversion="0.00100000" ingredient="I-3388"/>
	<Ingredient qty="2.270" uom="Kg" recipe="P-26020" invFactor="0.9080" conversion="2.20462000" ingredient="I-4657"/>
	<Ingredient qty="1.000" uom="Kg" recipe="P-26055" invFactor="1.1765" conversion="1.00000000" ingredient="I-2156"/>
	<Ingredient qty="5.000" uom="g" recipe="P-26055" invFactor="5.8824" conversion="1.00000000" ingredient="P-18907"/>
	<Ingredient qty="1.000" uom="CT" recipe="P-26057" invFactor="1.0000" conversion="1.00000000" ingredient="I-2159"/>
	<Ingredient qty="15.000" uom="ml" recipe="P-26057" invFactor="15.0000" conversion="0.00100000" ingredient="I-3388"/>
	<Ingredient qty="0.500" uom="g" recipe="P-26057" invFactor="0.5000" conversion="1.00000000" ingredient="P-18907"/>
	<Ingredient qty="250.000" uom="ml" recipe="P-26058" invFactor="250.0000" conversion="0.03381406" ingredient="I-1813"/>
	<Ingredient qty="750.000" uom="ml" recipe="P-26058" invFactor="750.0000" conversion="0.00100000" ingredient="I-3388"/>
	<Ingredient qty="400.000" uom="ml" recipe="P-26062" invFactor="13.3333" conversion="0.03381406" ingredient="I-6443"/>
	<Ingredient qty="15.000" uom="g" recipe="P-26062" invFactor="0.5000" conversion="1.00000000" ingredient="P-18907"/>
	<Ingredient qty="23.000" uom="Kg" recipe="P-26062" invFactor="0.7667" conversion="1.00000000" ingredient="P-44429"/>
	<Ingredient qty="300.000" uom="g" recipe="P-26062" invFactor="10.0000" conversion="1.00000000" ingredient="P-48495"/>
	<Ingredient qty="1.000" uom="Kg" recipe="P-26062" invFactor="0.0333" conversion="1000.00000000" ingredient="P-51535"/>
	<Ingredient qty="5.000" uom="Kg" recipe="P-26062" invFactor="0.1667" conversion="1.00000000" ingredient="P-57499"/>
	<Ingredient qty="250.000" uom="ml" recipe="P-26068" invFactor="208.3333" conversion="0.00100000" ingredient="I-3388"/>
	<Ingredient qty="15.000" uom="g" recipe="P-26068" invFactor="12.5000" conversion="0.00100000" ingredient="I-3660"/>
	<Ingredient qty="125.000" uom="g" recipe="P-26068" invFactor="104.1667" conversion="1.00000000" ingredient="I-8060"/>
	<Ingredient qty="15.000" uom="g" recipe="P-26068" invFactor="12.5000" conversion="1.00000000" ingredient="P-18907"/>
	<Ingredient qty="2.500" uom="Kg" recipe="P-26068" invFactor="2.0833" conversion="1.00000000" ingredient="P-19175"/>
	<Ingredient qty="10.000" uom="g" recipe="P-26069" invFactor="0.6667" conversion="0.00220462" ingredient="I-4463"/>
	<Ingredient qty="0.100" uom="g" recipe="P-26069" invFactor="0.0067" conversion="1.00000000" ingredient="P-18907"/>
	<Ingredient qty="5.000" uom="ml" recipe="P-26069" invFactor="0.3333" conversion="0.00100000" ingredient="P-26058"/>
	<Ingredient qty="4.000" uom="L" recipe="P-26074" invFactor="0.8000" conversion="1.00000000" ingredient="I-60772"/>
	<Ingredient qty="16.000" uom="oz" recipe="P-26074" invFactor="3.2000" conversion="0.92043824" ingredient="I-6443"/>
	<Ingredient qty="500.000" uom="ml" recipe="P-26074" invFactor="100.0000" conversion="0.00100000" ingredient="I-9382"/>
	<Ingredient qty="45.000" uom="g" recipe="P-26074" invFactor="9.0000" conversion="1.00000000" ingredient="P-18907"/>
	<Ingredient qty="50.000" uom="g" recipe="P-26074" invFactor="10.0000" conversion="1.00000000" ingredient="P-48495"/>
	<Ingredient qty="30.000" uom="g" recipe="P-26074" invFactor="6.0000" conversion="0.00100000" ingredient="P-7444"/>
	<Ingredient qty="5.000" uom="g" recipe="P-26075" invFactor="1.0000" conversion="0.00100000" ingredient="I-3660"/>
	<Ingredient qty="1.000" uom="g" recipe="P-26075" invFactor="0.2000" conversion="1.00000000" ingredient="I-6026"/>
	<Ingredient qty="1.000" uom="L" recipe="P-26075" invFactor="0.2000" conversion="1.00000000" ingredient="P-26074"/>
	<Ingredient qty="3.000" uom="Kg" recipe="P-26075" invFactor="0.6000" conversion="1.00000000" ingredient="P-34293"/>
	<Ingredient qty="750.000" uom="g" recipe="P-26075" invFactor="150.0000" conversion="1.00000000" ingredient="P-44475"/>
	<Ingredient qty="2.000" uom="Kg" recipe="P-26075" invFactor="0.4000" conversion="1.00000000" ingredient="P-9712"/>
	<Ingredient qty="0.045" uom="L" recipe="P-26140" invFactor="0.0305" conversion="1.00000000" ingredient="I-3388"/>
	<Ingredient qty="15.000" uom="g" recipe="P-26140" invFactor="10.1764" conversion="1.00000000" ingredient="I-6026"/>
	<Ingredient qty="0.120" uom="L" recipe="P-26140" invFactor="0.0814" conversion="35.21126761" ingredient="I-6443"/>
	<Ingredient qty="0.225" uom="Kg" recipe="P-26140" invFactor="0.1526" conversion="1.00000000" ingredient="P-39167"/>
	<Ingredient qty="0.100" uom="Kg" recipe="P-26140" invFactor="0.0678" conversion="1000.00000000" ingredient="P-44475"/>
	<Ingredient qty="0.075" uom="Kg" recipe="P-26140" invFactor="0.0509" conversion="1000.00000000" ingredient="P-48495"/>
	<Ingredient qty="0.500" uom="Kg" recipe="P-26140" invFactor="0.3392" conversion="1000.00000000" ingredient="P-56921"/>
	<Ingredient qty="1.250" uom="Kg" recipe="P-26140" invFactor="0.8480" conversion="1000.00000000" ingredient="P-56923"/>
	<Ingredient qty="60.000" uom="g" recipe="P-26140" invFactor="40.7056" conversion="0.00100000" ingredient="P-7444"/>
	<Ingredient qty="500.000" uom="ml" recipe="P-26205" invFactor="444.8399" conversion="0.00100000" ingredient="I-3388"/>
	<Ingredient qty="2.250" uom="Kg" recipe="P-26205" invFactor="2.0018" conversion="2.20462000" ingredient="I-4725"/>
	<Ingredient qty="20.000" uom="g" recipe="P-26205" invFactor="17.7936" conversion="1.00000000" ingredient="P-18907"/>
	<Ingredient qty="1.000" uom="CT" recipe="P-26514" invFactor="0.0182" conversion="1.00000000" ingredient="I-4341"/>
	<Ingredient qty="1.000" uom="lb" recipe="P-26557" invFactor="1.4286" conversion="1.00000000" ingredient="I-4465"/>
	<Ingredient qty="4.000" uom="L" recipe="P-28255" invFactor="0.9524" conversion="1.00000000" ingredient="I-60772"/>
	<Ingredient qty="250.000" uom="ml" recipe="P-28255" invFactor="59.5238" conversion="0.00100000" ingredient="I-9379"/>
	<Ingredient qty="4.000" uom="L" recipe="P-28262" invFactor="0.8889" conversion="1.00000000" ingredient="I-60772"/>
	<Ingredient qty="500.000" uom="ml" recipe="P-28262" invFactor="111.1111" conversion="0.00100000" ingredient="P-9519"/>
	<Ingredient qty="50.000" uom="ml" recipe="P-32244" invFactor="50.0000" conversion="1.00000000" ingredient="I-3447"/>
	<Ingredient qty="0.950" uom="L" recipe="P-32244" invFactor="0.9500" conversion="1.00000000" ingredient="I-60772"/>
	<Ingredient qty="10.000" uom="ml" recipe="P-32244" invFactor="10.0000" conversion="0.03381406" ingredient="I-6443"/>
	<Ingredient qty="946.000" uom="ml" recipe="P-32661" invFactor="30.4180" conversion="1.00000000" ingredient="I-3141"/>
	<Ingredient qty="31.000" uom="L" recipe="P-32661" invFactor="0.9968" conversion="1.00000000" ingredient="I-5983"/>
	<Ingredient qty="2.840" uom="L" recipe="P-32739" invFactor="0.9161" conversion="1.00000000" ingredient="I-3223"/>
	<Ingredient qty="20.000" uom="ml" recipe="P-32739" invFactor="6.4516" conversion="0.00200000" ingredient="I-3284"/>
	<Ingredient qty="250.000" uom="g" recipe="P-32739" invFactor="80.6452" conversion="0.00100000" ingredient="I-3660"/>
	<Ingredient qty="0.057" uom="Kg" recipe="P-34084" invFactor="2.8500" conversion="1.00000000" ingredient="I-65741"/>
	<Ingredient qty="44.000" uom="lb" recipe="P-34293" invFactor="2.2000" conversion="1.00000000" ingredient="P-9710"/>
	<Ingredient qty="1.000" uom="lb" recipe="P-34534" invFactor="0.1000" conversion="1.00000000" ingredient="I-4508"/>
	<Ingredient qty="800.000" uom="g" recipe="P-34892" invFactor="200.0000" conversion="0.00100000" ingredient="I-14773"/>
	<Ingredient qty="3.000" uom="L" recipe="P-34892" invFactor="0.7500" conversion="1.00000000" ingredient="I-5983"/>
	<Ingredient qty="1.360" uom="Kg" recipe="P-34892" invFactor="0.3400" conversion="1000.00000000" ingredient="I-8060"/>
	<Ingredient qty="0.120" uom="L" recipe="P-35251" invFactor="0.1560" conversion="35.21126761" ingredient="I-1813"/>
	<Ingredient qty="0.128" uom="Kg" recipe="P-35251" invFactor="0.1664" conversion="1.00000000" ingredient="I-2140"/>
	<Ingredient qty="0.320" uom="L" recipe="P-35251" invFactor="0.4161" conversion="1.00000000" ingredient="I-3387"/>
	<Ingredient qty="0.454" uom="Kg" recipe="P-35251" invFactor="0.5904" conversion="2.20462000" ingredient="I-4463"/>
	<Ingredient qty="30.000" uom="g" recipe="P-35251" invFactor="39.0117" conversion="1.00000000" ingredient="I-6026"/>
	<Ingredient qty="60.000" uom="ml" recipe="P-35251" invFactor="78.0234" conversion="0.00100000" ingredient="P-7444"/>
	<Ingredient qty="100.000" uom="ml" recipe="P-36089" invFactor="44.0917" conversion="0.00100000" ingredient="I-3388"/>
	<Ingredient qty="2.000" uom="g" recipe="P-36089" invFactor="0.8818" conversion="1.00000000" ingredient="I-3619"/>
	<Ingredient qty="5.000" uom="g" recipe="P-36089" invFactor="2.2046" conversion="0.00100000" ingredient="I-3643"/>
	<Ingredient qty="230.000" uom="g" recipe="P-36089" invFactor="101.4109" conversion="0.00220462" ingredient="I-4657"/>
	<Ingredient qty="2.500" uom="Kg" recipe="P-36089" invFactor="1.1023" conversion="2.20462000" ingredient="I-4894"/>
	<Ingredient qty="100.000" uom="ml" recipe="P-36089" invFactor="44.0917" conversion="0.00100000" ingredient="I-5983"/>
	<Ingredient qty="5.000" uom="g" recipe="P-36089" invFactor="2.2046" conversion="1.00000000" ingredient="I-6026"/>
	<Ingredient qty="1.900" uom="L" recipe="P-36090" invFactor="0.9500" conversion="1.00000000" ingredient="I-60772"/>
	<Ingredient qty="300.000" uom="g" recipe="P-36090" invFactor="150.0000" conversion="0.00100000" ingredient="P-36089"/>
	<Ingredient qty="1.000" uom="CT" recipe="P-37297" invFactor="1.0000" conversion="1.00000000" ingredient="I-2159"/>
	<Ingredient qty="11.550" uom="Kg" recipe="P-39167" invFactor="1.0490" conversion="2.20462000" ingredient="P-24452"/>
	<Ingredient qty="0.454" uom="Kg" recipe="P-41572" invFactor="0.4540" conversion="1000.00000000" ingredient="I-3632"/>
	<Ingredient qty="0.454" uom="Kg" recipe="P-41572" invFactor="0.4540" conversion="1.00000000" ingredient="I-5975"/>
	<Ingredient qty="0.125" uom="Kg" recipe="P-41572" invFactor="0.1250" conversion="1000.00000000" ingredient="I-6026"/>
	<Ingredient qty="0.500" uom="L" recipe="P-41573" invFactor="0.0625" conversion="1.00000000" ingredient="I-3388"/>
	<Ingredient qty="4.000" uom="Kg" recipe="P-41573" invFactor="0.5000" conversion="2.20462000" ingredient="I-3477"/>
	<Ingredient qty="4.000" uom="L" recipe="P-41573" invFactor="0.5000" conversion="1.00000000" ingredient="I-5983"/>
	<Ingredient qty="0.090" uom="L" recipe="P-41573" invFactor="0.0113" conversion="35.21126761" ingredient="I-6443"/>
	<Ingredient qty="0.400" uom="Kg" recipe="P-41573" invFactor="0.0500" conversion="1.00000000" ingredient="P-41572"/>
	<Ingredient qty="5.600" uom="L" recipe="P-44335" invFactor="0.5385" conversion="1.00000000" ingredient="I-23336"/>
	<Ingredient qty="10.000" uom="g" recipe="P-44335" invFactor="0.9615" conversion="1.00000000" ingredient="I-3621"/>
	<Ingredient qty="25.000" uom="g" recipe="P-44335" invFactor="2.4038" conversion="0.03527399" ingredient="I-3630"/>
	<Ingredient qty="2.000" uom="Kg" recipe="P-44335" invFactor="0.1923" conversion="1.00000000" ingredient="I-4978"/>
	<Ingredient qty="2.000" uom="Kg" recipe="P-44335" invFactor="0.1923" conversion="1.00000000" ingredient="I-5014"/>
	<Ingredient qty="75.000" uom="g" recipe="P-44335" invFactor="7.2115" conversion="1.00000000" ingredient="I-6026"/>
	<Ingredient qty="60.000" uom="ml" recipe="P-44335" invFactor="5.7692" conversion="0.00100000" ingredient="I-9382"/>
	<Ingredient qty="120.000" uom="g" recipe="P-44335" invFactor="11.5385" conversion="1.00000000" ingredient="P-48495"/>
	<Ingredient qty="2.000" uom="Kg" recipe="P-44335" invFactor="0.1923" conversion="2.20462000" ingredient="P-50552"/>
	<Ingredient qty="2.500" uom="Kg" recipe="P-44335" invFactor="0.2404" conversion="1.00000000" ingredient="P-50966"/>
	<Ingredient qty="56.000" uom="g" recipe="P-44335" invFactor="5.3846" conversion="1.00000000" ingredient="P-51536"/>
	<Ingredient qty="8.000" uom="CT" recipe="P-44392" invFactor="1.0000" conversion="1.00000000" ingredient="I-2159"/>
	<Ingredient qty="3.000" uom="g" recipe="P-44392" invFactor="0.3750" conversion="0.00100000" ingredient="I-3497"/>
	<Ingredient qty="0.200" uom="L" recipe="P-44392" invFactor="0.0250" conversion="1.00000000" ingredient="I-3698"/>
	<Ingredient qty="20.000" uom="L" recipe="P-44392" invFactor="2.5000" conversion="1.00000000" ingredient="I-5983"/>
	<Ingredient qty="1.000" uom="Kg" recipe="P-44429" invFactor="1.0000" conversion="1.00000000" ingredient="P-50587"/>
	<Ingredient qty="268.000" uom="g" recipe="P-44475" invFactor="1.2523" conversion="0.00220462" ingredient="I-4787"/>
	<Ingredient qty="5.000" uom="ml" recipe="P-44506" invFactor="1.2500" conversion="0.03381406" ingredient="I-1813"/>
	<Ingredient qty="1.000" uom="CT" recipe="P-44506" invFactor="0.2500" conversion="1.00000000" ingredient="I-4472"/>
	<Ingredient qty="5.000" uom="Kg" recipe="P-44592" invFactor="1.4286" conversion="1.00000000" ingredient="I-17667"/>
	<Ingredient qty="2.320" uom="Kg" recipe="P-44643" invFactor="1.1600" conversion="2.20462000" ingredient="I-33795"/>
	<Ingredient qty="5.000" uom="g" recipe="P-44643" invFactor="2.5000" conversion="1.00000000" ingredient="P-26019"/>
	<Ingredient qty="5.000" uom="Kg" recipe="P-44649" invFactor="0.5714" conversion="2.20462000" ingredient="I-19978"/>
	<Ingredient qty="100.000" uom="ml" recipe="P-44649" invFactor="11.4286" conversion="0.00100000" ingredient="I-3388"/>
	<Ingredient qty="5.000" uom="Kg" recipe="P-44649" invFactor="0.5714" conversion="2.20462000" ingredient="I-4900"/>
	<Ingredient qty="10.000" uom="g" recipe="P-44649" invFactor="1.1429" conversion="1.00000000" ingredient="P-18907"/>
	<Ingredient qty="1.000" uom="BUNCH" recipe="P-44728" invFactor="0.0222" conversion="1.00000000" ingredient="I-4772"/>
	<Ingredient qty="500.000" uom="ml" recipe="P-44737" invFactor="400.0000" conversion="0.00100000" ingredient="I-2217"/>
	<Ingredient qty="2.000" uom="Kg" recipe="P-44737" invFactor="1.6000" conversion="2.20462000" ingredient="I-4896"/>
	<Ingredient qty="1.000" uom="g" recipe="P-44737" invFactor="0.8000" conversion="1.00000000" ingredient="P-18907"/>
	<Ingredient qty="1.000" uom="Kg" recipe="P-44896" invFactor="2.0000" conversion="2.20462000" ingredient="I-4695"/>
	<Ingredient qty="30.000" uom="ml" recipe="P-44913" invFactor="18.7500" conversion="0.00100000" ingredient="I-3387"/>
	<Ingredient qty="7.000" uom="CT" recipe="P-44913" invFactor="4.3750" conversion="1.00000000" ingredient="I-4472"/>
	<Ingredient qty="0.900" uom="Kg" recipe="P-44913" invFactor="0.5625" conversion="1000.00000000" ingredient="I-4973"/>
	<Ingredient qty="0.045" uom="L" recipe="P-44913" invFactor="0.0281" conversion="35.21126761" ingredient="I-6443"/>
	<Ingredient qty="5.000" uom="g" recipe="P-44913" invFactor="3.1250" conversion="1.00000000" ingredient="P-18907"/>
	<Ingredient qty="500.000" uom="g" recipe="P-44964" invFactor="1.6667" conversion="1.00000000" ingredient="I-4699"/>
	<Ingredient qty="1.000" uom="Kg" recipe="P-45047" invFactor="2.0000" conversion="2.20462000" ingredient="I-4508"/>
	<Ingredient qty="5.000" uom="Kg" recipe="P-46076" invFactor="2.8571" conversion="1.00000000" ingredient="I-27410"/>
	<Ingredient qty="3.000" uom="Kg" recipe="P-46546" invFactor="1.0345" conversion="1.00000000" ingredient="I-2122"/>
	<Ingredient qty="454.000" uom="g" recipe="P-46862" invFactor="22.7000" conversion="1.00000000" ingredient="I-35791"/>
	<Ingredient qty="560.000" uom="g" recipe="P-46911" invFactor="160.0000" conversion="1.00000000" ingredient="I-51440"/>
	<Ingredient qty="15.000" uom="g" recipe="P-46911" invFactor="4.2857" conversion="1.00000000" ingredient="P-18907"/>
	<Ingredient qty="4.000" uom="Kg" recipe="P-46911" invFactor="1.1429" conversion="1.00000000" ingredient="P-66113"/>
	<Ingredient qty="1.000" uom="L" recipe="P-47541" invFactor="0.5714" conversion="1.00000000" ingredient="I-5983"/>
	<Ingredient qty="1.000" uom="Kg" recipe="P-47541" invFactor="0.5714" conversion="1.00000000" ingredient="I-6820"/>
	<Ingredient qty="40.000" uom="ml" recipe="P-47839" invFactor="18.1818" conversion="0.03381406" ingredient="I-1813"/>
	<Ingredient qty="0.400" uom="Kg" recipe="P-47839" invFactor="0.1818" conversion="1.00000000" ingredient="I-3660"/>
	<Ingredient qty="2.000" uom="Kg" recipe="P-47839" invFactor="0.9091" conversion="2.20462000" ingredient="I-4531"/>
	<Ingredient qty="0.500" uom="L" recipe="P-47839" invFactor="0.2273" conversion="1.00000000" ingredient="I-5983"/>
	<Ingredient qty="0.200" uom="L" recipe="P-47839" invFactor="0.0909" conversion="1.00000000" ingredient="P-47541"/>
	<Ingredient qty="100.000" uom="g" recipe="P-48495" invFactor="1.0000" conversion="1.00000000" ingredient="P-26514"/>
	<Ingredient qty="2.000" uom="Kg" recipe="P-48606" invFactor="1.4286" conversion="1.00000000" ingredient="I-19665"/>
	<Ingredient qty="48.000" uom="CT" recipe="P-48933" invFactor="8.4211" conversion="1.00000000" ingredient="I-4375"/>
	<Ingredient qty="20.000" uom="g" recipe="P-49552" invFactor="1.0000" conversion="0.00100000" ingredient="P-46076"/>
	<Ingredient qty="2.000" uom="Kg" recipe="P-50154" invFactor="0.4000" conversion="1.00000000" ingredient="I-3360"/>
	<Ingredient qty="2.800" uom="L" recipe="P-50154" invFactor="0.5600" conversion="1.00000000" ingredient="I-5983"/>
	<Ingredient qty="5.000" uom="ml" recipe="P-50231" invFactor="100.0000" conversion="0.00100000" ingredient="I-3387"/>
	<Ingredient qty="0.010" uom="Kg" recipe="P-50231" invFactor="0.2000" conversion="1000.00000000" ingredient="I-8060"/>
	<Ingredient qty="5.000" uom="g" recipe="P-50231" invFactor="100.0000" conversion="1.00000000" ingredient="P-18907"/>
	<Ingredient qty="0.050" uom="Kg" recipe="P-50231" invFactor="1.0000" conversion="2.20462000" ingredient="P-26557"/>
	<Ingredient qty="35.000" uom="ml" recipe="P-50287" invFactor="3.5000" conversion="0.00100000" ingredient="I-3387"/>
	<Ingredient qty="250.000" uom="g" recipe="P-50287" invFactor="25.0000" conversion="0.00100000" ingredient="P-20239"/>
	<Ingredient qty="2.000" uom="g" recipe="P-50287" invFactor="0.2000" conversion="1.00000000" ingredient="P-25993"/>
	<Ingredient qty="500.000" uom="g" recipe="P-50287" invFactor="50.0000" conversion="0.00100000" ingredient="P-26068"/>
	<Ingredient qty="150.000" uom="g" recipe="P-50287" invFactor="15.0000" conversion="0.00100000" ingredient="P-44896"/>
	<Ingredient qty="9.500" uom="Kg" recipe="P-50287" invFactor="0.9500" conversion="1.00000000" ingredient="P-50288"/>
	<Ingredient qty="50.000" uom="g" recipe="P-50287" invFactor="5.0000" conversion="1.00000000" ingredient="P-50289"/>
	<Ingredient qty="5.000" uom="Kg" recipe="P-50288" invFactor="0.5000" conversion="35.27399000" ingredient="I-11185"/>
	<Ingredient qty="50.000" uom="ml" recipe="P-50288" invFactor="5.0000" conversion="0.00100000" ingredient="I-3387"/>
	<Ingredient qty="10.000" uom="L" recipe="P-50288" invFactor="1.0000" conversion="1.00000000" ingredient="I-5983"/>
	<Ingredient qty="7.000" uom="g" recipe="P-50288" invFactor="0.7000" conversion="1.00000000" ingredient="P-26019"/>
	<Ingredient qty="30.000" uom="g" recipe="P-50289" invFactor="0.3000" conversion="0.00100000" ingredient="I-12176"/>
	<Ingredient qty="30.000" uom="ml" recipe="P-50289" invFactor="0.3000" conversion="0.00100000" ingredient="I-3387"/>
	<Ingredient qty="100.000" uom="g" recipe="P-50289" invFactor="1.0000" conversion="0.00100000" ingredient="I-3588"/>
	<Ingredient qty="20.000" uom="g" recipe="P-50289" invFactor="0.2000" conversion="0.00100000" ingredient="I-3643"/>
	<Ingredient qty="150.000" uom="g" recipe="P-50337" invFactor="27.2727" conversion="0.00100000" ingredient="I-3660"/>
	<Ingredient qty="25.000" uom="g" recipe="P-50337" invFactor="4.5455" conversion="0.00220462" ingredient="I-4847"/>
	<Ingredient qty="5.000" uom="Kg" recipe="P-50337" invFactor="0.9091" conversion="1.00000000" ingredient="I-5012"/>
	<Ingredient qty="500.000" uom="ml" recipe="P-50337" invFactor="90.9091" conversion="0.00100000" ingredient="I-5983"/>
	<Ingredient qty="100.000" uom="ml" recipe="P-50337" invFactor="18.1818" conversion="0.00100000" ingredient="P-50495"/>
	<Ingredient qty="1000.000" uom="ml" recipe="P-50495" invFactor="500.0000" conversion="0.00100000" ingredient="I-5983"/>
	<Ingredient qty="1000.000" uom="g" recipe="P-50495" invFactor="500.0000" conversion="0.00100000" ingredient="I-6820"/>
	<Ingredient qty="120.000" uom="ml" recipe="P-50505" invFactor="60.0000" conversion="0.00100000" ingredient="P-50154"/>
	<Ingredient qty="100.000" uom="g" recipe="P-50535" invFactor="2.3256" conversion="1.00000000" ingredient="I-3619"/>
	<Ingredient qty="1.350" uom="Kg" recipe="P-50535" invFactor="0.0314" conversion="1.00000000" ingredient="I-3660"/>
	<Ingredient qty="1.600" uom="L" recipe="P-50535" invFactor="0.0372" conversion="1.00000000" ingredient="I-3695"/>
	<Ingredient qty="200.000" uom="g" recipe="P-50535" invFactor="4.6512" conversion="0.00220462" ingredient="I-4508"/>
	<Ingredient qty="600.000" uom="g" recipe="P-50535" invFactor="13.9535" conversion="0.00220462" ingredient="I-4657"/>
	<Ingredient qty="600.000" uom="g" recipe="P-50535" invFactor="13.9535" conversion="0.00220462" ingredient="I-4743"/>
	<Ingredient qty="20.000" uom="CT" recipe="P-50535" invFactor="0.4651" conversion="1.00000000" ingredient="I-4764"/>
	<Ingredient qty="40.000" uom="L" recipe="P-50535" invFactor="0.9302" conversion="1.00000000" ingredient="I-5983"/>
	<Ingredient qty="2.200" uom="Kg" recipe="P-50535" invFactor="0.0512" conversion="1000.00000000" ingredient="I-6026"/>
	<Ingredient qty="50.000" uom="ml" recipe="P-50543" invFactor="100.0000" conversion="0.00100000" ingredient="I-3692"/>
	<Ingredient qty="5.000" uom="g" recipe="P-50543" invFactor="10.0000" conversion="1.00000000" ingredient="P-18907"/>
	<Ingredient qty="15.000" uom="g" recipe="P-50543" invFactor="30.0000" conversion="0.00100000" ingredient="P-45047"/>
	<Ingredient qty="0.500" uom="Kg" recipe="P-50543" invFactor="1.0000" conversion="1.00000000" ingredient="P-50966"/>
	<Ingredient qty="5.000" uom="ml" recipe="P-50543" invFactor="10.0000" conversion="0.00100000" ingredient="P-7444"/>
	<Ingredient qty="25.000" uom="lb" recipe="P-50552" invFactor="1.0870" conversion="1.00000000" ingredient="I-4745"/>
	<Ingredient qty="10.000" uom="Kg" recipe="P-50587" invFactor="1.0309" conversion="2.20462000" ingredient="I-4933"/>
	<Ingredient qty="1050.000" uom="g" recipe="P-50636" invFactor="1.6154" conversion="0.00555000" ingredient="I-4507"/>
	<Ingredient qty="454.000" uom="g" recipe="P-50676" invFactor="1.5133" conversion="0.00220462" ingredient="I-4919"/>
	<Ingredient qty="10.000" uom="lb" recipe="P-50695" invFactor="1.1765" conversion="1.00000000" ingredient="I-4673"/>
	<Ingredient qty="1.000" uom="Kg" recipe="P-50720" invFactor="0.3333" conversion="2.20462000" ingredient="I-4852"/>
	<Ingredient qty="2.000" uom="Kg" recipe="P-50720" invFactor="0.6667" conversion="1.00000000" ingredient="P-26062"/>
	<Ingredient qty="1.000" uom="SHEET" recipe="P-50725" invFactor="0.0313" conversion="1.00000000" ingredient="I-7055"/>
	<Ingredient qty="125.000" uom="ml" recipe="P-50739" invFactor="50.0000" conversion="0.03381406" ingredient="I-1813"/>
	<Ingredient qty="2.500" uom="Kg" recipe="P-50739" invFactor="1.0000" conversion="1.00000000" ingredient="I-29389"/>
	<Ingredient qty="5.000" uom="g" recipe="P-50739" invFactor="2.0000" conversion="1.00000000" ingredient="I-2979"/>
	<Ingredient qty="30.000" uom="ml" recipe="P-50739" invFactor="12.0000" conversion="0.00200000" ingredient="I-3284"/>
	<Ingredient qty="325.000" uom="g" recipe="P-50739" invFactor="130.0000" conversion="0.00100000" ingredient="I-3660"/>
	<Ingredient qty="250.000" uom="ml" recipe="P-50739" invFactor="100.0000" conversion="0.00100000" ingredient="I-5983"/>
	<Ingredient qty="125.000" uom="ml" recipe="P-50739" invFactor="50.0000" conversion="0.00100000" ingredient="P-50495"/>
	<Ingredient qty="90.000" uom="ml" recipe="P-50744" invFactor="14.5161" conversion="0.03381406" ingredient="I-1813"/>
	<Ingredient qty="1.000" uom="Kg" recipe="P-50744" invFactor="0.1613" conversion="2.20462000" ingredient="I-4894"/>
	<Ingredient qty="5.000" uom="L" recipe="P-50744" invFactor="0.8065" conversion="1.00000000" ingredient="I-60772"/>
	<Ingredient qty="10.000" uom="g" recipe="P-50744" invFactor="1.6129" conversion="1.00000000" ingredient="P-25993"/>
	<Ingredient qty="200.000" uom="g" recipe="P-50744" invFactor="32.2581" conversion="0.00100000" ingredient="P-26020"/>
	<Ingredient qty="1.000" uom="bag" recipe="P-50853" invFactor="0.0021" conversion="1.00000000" ingredient="I-19283"/>
	<Ingredient qty="1.000" uom="Kg" recipe="P-50966" invFactor="1.0000" conversion="2.20462000" ingredient="I-17159"/>
	<Ingredient qty="6.000" uom="CT" recipe="P-51086" invFactor="1.0000" conversion="1.00000000" ingredient="I-1197"/>
	<Ingredient qty="7.600" uom="Kg" recipe="P-51131" invFactor="0.9500" conversion="1.00000000" ingredient="I-3851"/>
	<Ingredient qty="10.000" uom="L" recipe="P-51131" invFactor="1.2500" conversion="1.00000000" ingredient="P-50535"/>
	<Ingredient qty="5.000" uom="Kg" recipe="P-51242" invFactor="1.2500" conversion="2.20462000" ingredient="I-13903"/>
	<Ingredient qty="50.000" uom="ml" recipe="P-51382" invFactor="1.1364" conversion="0.00100000" ingredient="I-3387"/>
	<Ingredient qty="5.000" uom="Kg" recipe="P-51382" invFactor="0.1136" conversion="2.20462000" ingredient="I-4933"/>
	<Ingredient qty="10.000" uom="g" recipe="P-51382" invFactor="0.2273" conversion="1.00000000" ingredient="P-18907"/>
	<Ingredient qty="20.000" uom="g" recipe="P-51508" invFactor="10.0000" conversion="0.00100000" ingredient="P-34084"/>
	<Ingredient qty="1.000" uom="Kg" recipe="P-51535" invFactor="0.0014" conversion="2.20462000" ingredient="I-4787"/>
	<Ingredient qty="454.000" uom="g" recipe="P-51536" invFactor="1.3969" conversion="1.00000000" ingredient="I-3314"/>
	<Ingredient qty="1.000" uom="Kg" recipe="P-51537" invFactor="1.5385" conversion="2.20462000" ingredient="I-4848"/>
	<Ingredient qty="5.000" uom="g" recipe="P-52042" invFactor="5.5556" conversion="1.00000000" ingredient="I-6026"/>
	<Ingredient qty="100.000" uom="g" recipe="P-52042" invFactor="111.1111" conversion="0.00100000" ingredient="I-6820"/>
	<Ingredient qty="1.000" uom="Kg" recipe="P-52042" invFactor="1.1111" conversion="1.00000000" ingredient="I-7388"/>
	<Ingredient qty="90.000" uom="g" recipe="P-52943" invFactor="1.8000" conversion="0.01259785" ingredient="I-4341"/>
	<Ingredient qty="150.000" uom="g" recipe="P-55682" invFactor="15.0000" conversion="0.00100000" ingredient="I-2911"/>
	<Ingredient qty="5.000" uom="Kg" recipe="P-55682" invFactor="0.5000" conversion="0.94667000" ingredient="I-3145"/>
	<Ingredient qty="100.000" uom="ml" recipe="P-55682" invFactor="10.0000" conversion="0.00100000" ingredient="I-3695"/>
	<Ingredient qty="100.000" uom="g" recipe="P-55682" invFactor="10.0000" conversion="1.00000000" ingredient="I-5978"/>
	<Ingredient qty="150.000" uom="g" recipe="P-55682" invFactor="15.0000" conversion="1.00000000" ingredient="I-6832"/>
	<Ingredient qty="175.000" uom="g" recipe="P-55682" invFactor="17.5000" conversion="1.00000000" ingredient="P-18907"/>
	<Ingredient qty="6.000" uom="L" recipe="P-55682" invFactor="0.6000" conversion="1.00000000" ingredient="P-32661"/>
	<Ingredient qty="250.000" uom="ml" recipe="P-55682" invFactor="25.0000" conversion="0.00100000" ingredient="P-7444"/>
	<Ingredient qty="2.500" uom="lb" recipe="P-55682" invFactor="0.2500" conversion="1.00000000" ingredient="P-9746"/>
	<Ingredient qty="2.000" uom="lb" recipe="P-55682" invFactor="0.2000" conversion="1.00000000" ingredient="P-9768"/>
	<Ingredient qty="454.000" uom="g" recipe="P-56290" invFactor="1.2500" conversion="0.00220462" ingredient="I-4792"/>
	<Ingredient qty="2.000" uom="Kg" recipe="P-56398" invFactor="0.4444" conversion="1000.00000000" ingredient="I-4973"/>
	<Ingredient qty="50.000" uom="ml" recipe="P-56398" invFactor="11.1111" conversion="0.03381406" ingredient="I-6443"/>
	<Ingredient qty="500.000" uom="g" recipe="P-56398" invFactor="111.1111" conversion="0.00100000" ingredient="P-26062"/>
	<Ingredient qty="2.000" uom="Kg" recipe="P-56398" invFactor="0.4444" conversion="1.00000000" ingredient="P-44913"/>
	<Ingredient qty="1.000" uom="L" recipe="P-56455" invFactor="0.2000" conversion="1000.00000000" ingredient="I-3368"/>
	<Ingredient qty="4.000" uom="L" recipe="P-56455" invFactor="0.8000" conversion="1.00000000" ingredient="I-60772"/>
	<Ingredient qty="75.000" uom="ml" recipe="P-56778" invFactor="100.0000" conversion="0.00100000" ingredient="I-3387"/>
	<Ingredient qty="1.000" uom="Kg" recipe="P-56778" invFactor="1.3333" conversion="2.20462000" ingredient="I-4729"/>
	<Ingredient qty="5.000" uom="g" recipe="P-56778" invFactor="6.6667" conversion="1.00000000" ingredient="P-26019"/>
	<Ingredient qty="50.000" uom="g" recipe="P-56778" invFactor="66.6667" conversion="1.00000000" ingredient="P-44728"/>
	<Ingredient qty="50.000" uom="ml" recipe="P-56778" invFactor="66.6667" conversion="0.00100000" ingredient="P-7444"/>
	<Ingredient qty="100.000" uom="g" recipe="P-56778" invFactor="133.3333" conversion="0.00100000" ingredient="P-9738"/>
	<Ingredient qty="1.000" uom="Kg" recipe="P-56921" invFactor="0.0012" conversion="2.20462000" ingredient="I-30068"/>
	<Ingredient qty="15.000" uom="ml" recipe="P-56923" invFactor="0.0182" conversion="0.00100000" ingredient="I-3387"/>
	<Ingredient qty="1.000" uom="Kg" recipe="P-56923" invFactor="0.0012" conversion="2.20462000" ingredient="I-4920"/>
	<Ingredient qty="5.000" uom="g" recipe="P-56923" invFactor="0.0061" conversion="1.00000000" ingredient="P-18907"/>
	<Ingredient qty="1.000" uom="lb" recipe="P-57213" invFactor="1.2500" conversion="2.49226576" ingredient="I-4271"/>
	<Ingredient qty="11.500" uom="Kg" recipe="P-57499" invFactor="1.0455" conversion="1.00000000" ingredient="P-19175"/>
	<Ingredient qty="2.000" uom="Kg" recipe="P-58226" invFactor="1.2500" conversion="2.20462000" ingredient="I-4437"/>
	<Ingredient qty="25.000" uom="ml" recipe="P-58403" invFactor="14.2857" conversion="1.00000000" ingredient="I-26014"/>
	<Ingredient qty="5.000" uom="g" recipe="P-58403" invFactor="2.8571" conversion="0.00100000" ingredient="I-3624"/>
	<Ingredient qty="5.000" uom="g" recipe="P-58403" invFactor="2.8571" conversion="1.00000000" ingredient="I-3638"/>
	<Ingredient qty="100.000" uom="g" recipe="P-58403" invFactor="57.1429" conversion="0.00220462" ingredient="I-4488"/>
	<Ingredient qty="350.000" uom="g" recipe="P-58403" invFactor="200.0000" conversion="1.00000000" ingredient="I-60843"/>
	<Ingredient qty="200.000" uom="g" recipe="P-58403" invFactor="114.2857" conversion="0.00100000" ingredient="P-20239"/>
	<Ingredient qty="300.000" uom="g" recipe="P-58403" invFactor="171.4286" conversion="0.00220462" ingredient="P-24452"/>
	<Ingredient qty="10.000" uom="g" recipe="P-58403" invFactor="5.7143" conversion="0.00100000" ingredient="P-26020"/>
	<Ingredient qty="15.000" uom="g" recipe="P-58403" invFactor="8.5714" conversion="1.00000000" ingredient="P-50676"/>
	<Ingredient qty="10.000" uom="g" recipe="P-58403" invFactor="5.7143" conversion="0.00100000" ingredient="P-51537"/>
	<Ingredient qty="150.000" uom="g" recipe="P-58403" invFactor="85.7143" conversion="0.00220462" ingredient="P-57213"/>
	<Ingredient qty="700.000" uom="g" recipe="P-58403" invFactor="400.0000" conversion="0.00100000" ingredient="P-58226"/>
	<Ingredient qty="125.000" uom="ml" recipe="P-58949" invFactor="38.2497" conversion="0.03381406" ingredient="I-1813"/>
	<Ingredient qty="10.000" uom="ml" recipe="P-58949" invFactor="3.0600" conversion="0.00200000" ingredient="I-3284"/>
	<Ingredient qty="0.250" uom="Kg" recipe="P-58949" invFactor="0.0765" conversion="1.00000000" ingredient="I-3660"/>
	<Ingredient qty="2.250" uom="Kg" recipe="P-58949" invFactor="0.6885" conversion="1.00000000" ingredient="I-4907"/>
	<Ingredient qty="0.625" uom="L" recipe="P-58949" invFactor="0.1912" conversion="1.00000000" ingredient="I-5983"/>
	<Ingredient qty="60.000" uom="g" recipe="P-58949" invFactor="18.3599" conversion="0.00100000" ingredient="I-6820"/>
	<Ingredient qty="16.000" uom="Kg" recipe="P-61821" invFactor="1.0323" conversion="1.00000000" ingredient="I-13800"/>
	<Ingredient qty="25.000" uom="ml" recipe="P-61843" invFactor="50.0000" conversion="0.00100000" ingredient="I-3388"/>
	<Ingredient qty="5.000" uom="g" recipe="P-61843" invFactor="10.0000" conversion="0.03527399" ingredient="I-3630"/>
	<Ingredient qty="0.300" uom="Kg" recipe="P-61843" invFactor="0.6000" conversion="2.20462000" ingredient="I-4819"/>
	<Ingredient qty="10.000" uom="g" recipe="P-61843" invFactor="20.0000" conversion="0.00100000" ingredient="I-5975"/>
	<Ingredient qty="5.000" uom="g" recipe="P-61843" invFactor="10.0000" conversion="0.00100000" ingredient="P-25993"/>
	<Ingredient qty="0.150" uom="Kg" recipe="P-61843" invFactor="0.3000" conversion="1000.00000000" ingredient="P-44964"/>
	<Ingredient qty="0.100" uom="Kg" recipe="P-61843" invFactor="0.2000" conversion="1000.00000000" ingredient="P-56290"/>
	<Ingredient qty="90.000" uom="ml" recipe="P-64884" invFactor="12.8571" conversion="1.00000000" ingredient="I-20348"/>
	<Ingredient qty="600.000" uom="g" recipe="P-64884" invFactor="85.7143" conversion="0.00100000" ingredient="I-3660"/>
	<Ingredient qty="4.000" uom="L" recipe="P-64884" invFactor="0.5714" conversion="1.00000000" ingredient="I-5983"/>
	<Ingredient qty="500.000" uom="g" recipe="P-64884" invFactor="71.4286" conversion="0.00100000" ingredient="I-6820"/>
	<Ingredient qty="5.000" uom="Kg" recipe="P-64884" invFactor="0.7143" conversion="1.00000000" ingredient="I-7185"/>
	<Ingredient qty="700.000" uom="g" recipe="P-65937" invFactor="170.7317" conversion="1.00000000" ingredient="I-40936"/>
	<Ingredient qty="5.000" uom="g" recipe="P-65937" invFactor="1.2195" conversion="1.00000000" ingredient="P-18907"/>
	<Ingredient qty="4.000" uom="Kg" recipe="P-65937" invFactor="0.9756" conversion="1.00000000" ingredient="P-48606"/>
	<Ingredient qty="2.400" uom="Kg" recipe="P-66113" invFactor="1.2000" conversion="2.20462000" ingredient="I-6810"/>
	<Ingredient qty="100.000" uom="ml" recipe="P-68106" invFactor="20.0000" conversion="0.00100000" ingredient="I-3671"/>
	<Ingredient qty="5.000" uom="Kg" recipe="P-68106" invFactor="1.0000" conversion="1.00000000" ingredient="I-5015"/>
	<Ingredient qty="1.000" uom="each" recipe="P-69444" invFactor="1.1765" conversion="1.00000000" ingredient="I-68699"/>
	<Ingredient qty="5.000" uom="g" recipe="P-69444" invFactor="5.8824" conversion="1.00000000" ingredient="P-18907"/>
	<Ingredient qty="4.500" uom="Kg" recipe="P-6975" invFactor="0.5000" conversion="2.20462000" ingredient="I-3477"/>
	<Ingredient qty="6.500" uom="L" recipe="P-6975" invFactor="0.7222" conversion="1.00000000" ingredient="I-5983"/>
	<Ingredient qty="40.000" uom="g" recipe="P-6975" invFactor="4.4444" conversion="1.00000000" ingredient="P-18907"/>
	<Ingredient qty="500.000" uom="ml" recipe="P-7139" invFactor="250.0000" conversion="0.03381406" ingredient="I-1813"/>
	<Ingredient qty="1.500" uom="L" recipe="P-7139" invFactor="0.7500" conversion="1.00000000" ingredient="I-3387"/>
	<Ingredient qty="6.000" uom="g" recipe="P-7139" invFactor="3.0000" conversion="1.00000000" ingredient="I-3623"/>
	<Ingredient qty="1.000" uom="L" recipe="P-7444" invFactor="0.2500" conversion="1.00000000" ingredient="I-3387"/>
	<Ingredient qty="5.000" uom="lb" recipe="P-7444" invFactor="1.2500" conversion="1.00000000" ingredient="I-4657"/>
	<Ingredient qty="20.000" uom="g" recipe="P-8202" invFactor="0.0500" conversion="0.00100000" ingredient="I-3497"/>
	<Ingredient qty="90.000" uom="g" recipe="P-8202" invFactor="0.2250" conversion="0.00100000" ingredient="I-3622"/>
	<Ingredient qty="90.000" uom="g" recipe="P-8202" invFactor="0.2250" conversion="0.03527399" ingredient="I-3630"/>
	<Ingredient qty="10.000" uom="g" recipe="P-8202" invFactor="0.0250" conversion="0.00100000" ingredient="I-3643"/>
	<Ingredient qty="100.000" uom="g" recipe="P-8202" invFactor="0.2500" conversion="0.00100000" ingredient="I-3657"/>
	<Ingredient qty="90.000" uom="g" recipe="P-8202" invFactor="0.2250" conversion="1.00000000" ingredient="I-5978"/>
	<Ingredient qty="2.000" uom="L" recipe="P-8205" invFactor="0.3571" conversion="1.00000000" ingredient="I-5983"/>
	<Ingredient qty="8.000" uom="Kg" recipe="P-8205" invFactor="1.4286" conversion="1.00000000" ingredient="P-51131"/>
	<Ingredient qty="400.000" uom="g" recipe="P-8205" invFactor="71.4286" conversion="1.00000000" ingredient="P-8202"/>
	<Ingredient qty="4.000" uom="L" recipe="P-9519" invFactor="1.0000" conversion="1.00000000" ingredient="I-3387"/>
	<Ingredient qty="275.000" uom="ml" recipe="P-9519" invFactor="68.7500" conversion="0.00100000" ingredient="I-5983"/>
	<Ingredient qty="200.000" uom="ml" recipe="P-9519" invFactor="50.0000" conversion="0.03381406" ingredient="I-6443"/>
	<Ingredient qty="7.000" uom="ml" recipe="P-9519" invFactor="1.7500" conversion="0.00100000" ingredient="I-9382"/>
	<Ingredient qty="5.000" uom="g" recipe="P-9519" invFactor="1.2500" conversion="1.00000000" ingredient="P-18907"/>
	<Ingredient qty="150.000" uom="g" recipe="P-9519" invFactor="37.5000" conversion="1.00000000" ingredient="P-44475"/>
	<Ingredient qty="200.000" uom="g" recipe="P-9519" invFactor="50.0000" conversion="1.00000000" ingredient="P-44728"/>
	<Ingredient qty="250.000" uom="g" recipe="P-9519" invFactor="62.5000" conversion="0.00100000" ingredient="P-45047"/>
	<Ingredient qty="100.000" uom="g" recipe="P-9519" invFactor="25.0000" conversion="1.00000000" ingredient="P-48495"/>
	<Ingredient qty="30.000" uom="g" recipe="P-9519" invFactor="7.5000" conversion="0.00100000" ingredient="P-7444"/>
	<Ingredient qty="50.000" uom="lb" recipe="P-9710" invFactor="1.2500" conversion="1.00000000" ingredient="I-4550"/>
	<Ingredient qty="50.000" uom="lb" recipe="P-9712" invFactor="1.2500" conversion="1.00000000" ingredient="I-4556"/>
	<Ingredient qty="22.700" uom="Kg" recipe="P-9713" invFactor="1.1762" conversion="2.20462000" ingredient="I-4589"/>
	<Ingredient qty="1.000" uom="Kg" recipe="P-9714" invFactor="1.1111" conversion="1.00000000" ingredient="P-9713"/>
	<Ingredient qty="25.000" uom="lb" recipe="P-9734" invFactor="1.2303" conversion="1.00000000" ingredient="I-4786"/>
	<Ingredient qty="1.000" uom="Kg" recipe="P-9738" invFactor="1.0000" conversion="1.00000000" ingredient="P-48933"/>
	<Ingredient qty="1.000" uom="Kg" recipe="P-9741" invFactor="1.0000" conversion="1.00000000" ingredient="P-48933"/>
	<Ingredient qty="50.000" uom="lb" recipe="P-9745" invFactor="1.0965" conversion="1.00000000" ingredient="I-17150"/>
	<Ingredient qty="1.000" uom="lb" recipe="P-9746" invFactor="1.0000" conversion="1.00000000" ingredient="P-9745"/>
	<Ingredient qty="1.000" uom="lb" recipe="P-9768" invFactor="2.0000" conversion="1.00000000" ingredient="P-9734"/>
	<Ingredient qty="50.000" uom="ml" recipe="P-9857" invFactor="3.1494" conversion="0.00100000" ingredient="I-3386"/>
	<Ingredient qty="18.000" uom="Kg" recipe="P-9857" invFactor="1.1338" conversion="2.20462000" ingredient="I-4913"/>
	<Ingredient qty="25.000" uom="g" recipe="P-9857" invFactor="1.5747" conversion="1.00000000" ingredient="P-18907"/>
	<Ingredient qty="45.000" uom="ml" recipe="R-36646" invFactor="1.0000" conversion="0.00100000" ingredient="I-3670"/>
	<Ingredient qty="60.000" uom="ml" recipe="R-36646" invFactor="1.0000" conversion="0.00100000" ingredient="P-47839"/>
	<Ingredient qty="2.000" uom="each" recipe="R-36646" invFactor="1.0000" conversion="1.00000000" ingredient="P-50505"/>
	<Ingredient qty="1.000" uom="CT" recipe="R-36647" invFactor="1.0000" conversion="1.00000000" ingredient="I-9341"/>
	<Ingredient qty="25.000" uom="ml" recipe="R-36647" invFactor="1.0000" conversion="0.00100000" ingredient="P-32244"/>
	<Ingredient qty="1.000" uom="each" recipe="R-36647" invFactor="1.0000" conversion="1.00000000" ingredient="P-44506"/>
	<Ingredient qty="40.000" uom="g" recipe="R-36647" invFactor="1.0000" conversion="0.00100000" ingredient="P-50720"/>
	<Ingredient qty="5.000" uom="g" recipe="R-36647" invFactor="1.0000" conversion="1.00000000" ingredient="P-52943"/>
	<Ingredient qty="55.000" uom="g" recipe="R-36647" invFactor="1.0000" conversion="0.00100000" ingredient="P-55682"/>
	<Ingredient qty="110.000" uom="g" recipe="R-36647" invFactor="1.0000" conversion="0.00100000" ingredient="P-69444"/>
	<Ingredient qty="1.000" uom="CT" recipe="R-44024" invFactor="1.0000" conversion="1.00000000" ingredient="I-1152"/>
	<Ingredient qty="0.500" uom="g" recipe="R-44024" invFactor="1.0000" conversion="1.00000000" ingredient="P-18907"/>
	<Ingredient qty="90.000" uom="g" recipe="R-44024" invFactor="1.0000" conversion="0.00100000" ingredient="P-26055"/>
	<Ingredient qty="20.000" uom="g" recipe="R-44024" invFactor="1.0000" conversion="1.00000000" ingredient="P-26069"/>
	<Ingredient qty="15.000" uom="ml" recipe="R-44024" invFactor="1.0000" conversion="0.00100000" ingredient="P-34892"/>
	<Ingredient qty="65.000" uom="g" recipe="R-44024" invFactor="1.0000" conversion="0.00100000" ingredient="P-44592"/>
	<Ingredient qty="5.000" uom="g" recipe="R-44650" invFactor="1.0000" conversion="0.00220462" ingredient="I-4695"/>
	<Ingredient qty="15.000" uom="ml" recipe="R-44650" invFactor="1.0000" conversion="0.00100000" ingredient="I-9379"/>
	<Ingredient qty="10.000" uom="g" recipe="R-44650" invFactor="1.0000" conversion="1.00000000" ingredient="P-26069"/>
	<Ingredient qty="10.000" uom="ml" recipe="R-44650" invFactor="1.0000" conversion="0.00100000" ingredient="P-28255"/>
	<Ingredient qty="30.000" uom="ml" recipe="R-44650" invFactor="1.0000" conversion="0.00100000" ingredient="P-28262"/>
	<Ingredient qty="2.000" uom="each" recipe="R-44650" invFactor="1.0000" conversion="1.00000000" ingredient="P-44392"/>
	<Ingredient qty="200.000" uom="g" recipe="R-44650" invFactor="1.0000" conversion="0.00100000" ingredient="P-44643"/>
	<Ingredient qty="100.000" uom="g" recipe="R-44650" invFactor="1.0000" conversion="0.00100000" ingredient="P-44649"/>
	<Ingredient qty="7.000" uom="g" recipe="R-44650" invFactor="1.0000" conversion="0.00100000" ingredient="P-9714"/>
	<Ingredient qty="1.000" uom="each" recipe="R-44738" invFactor="1.0000" conversion="1.00000000" ingredient="P-51382"/>
	<Ingredient qty="10.000" uom="g" recipe="R-47287" invFactor="1.0000" conversion="0.00220462" ingredient="I-10923"/>
	<Ingredient qty="30.000" uom="g" recipe="R-47287" invFactor="1.0000" conversion="0.00100000" ingredient="I-14177"/>
	<Ingredient qty="180.000" uom="g" recipe="R-47287" invFactor="1.0000" conversion="0.00100000" ingredient="I-2166"/>
	<Ingredient qty="30.000" uom="g" recipe="R-47287" invFactor="1.0000" conversion="0.00220462" ingredient="I-4725"/>
	<Ingredient qty="3.000" uom="ml" recipe="R-47287" invFactor="1.0000" conversion="0.00100000" ingredient="P-7139"/>
	<Ingredient qty="40.000" uom="g" recipe="R-48357" invFactor="1.0000" conversion="0.00220462" ingredient="I-11101"/>
	<Ingredient qty="1.000" uom="CT" recipe="R-48357" invFactor="1.0000" conversion="1.00000000" ingredient="I-1197"/>
	<Ingredient qty="60.000" uom="ml" recipe="R-48357" invFactor="1.0000" conversion="0.00100000" ingredient="P-34892"/>
	<Ingredient qty="2.000" uom="each" recipe="R-48357" invFactor="1.0000" conversion="1.00000000" ingredient="P-37297"/>
	<Ingredient qty="1.000" uom="CT" recipe="R-48488" invFactor="1.0000" conversion="1.00000000" ingredient="I-1152"/>
	<Ingredient qty="20.000" uom="g" recipe="R-48488" invFactor="1.0000" conversion="0.00100000" ingredient="I-14179"/>
	<Ingredient qty="50.000" uom="g" recipe="R-48488" invFactor="1.0000" conversion="0.00093884" ingredient="I-3146"/>
	<Ingredient qty="5.000" uom="ml" recipe="R-48488" invFactor="1.0000" conversion="0.00100000" ingredient="I-3388"/>
	<Ingredient qty="1.000" uom="ea" recipe="R-48488" invFactor="1.0000" conversion="1.00000000" ingredient="P-26057"/>
	<Ingredient qty="35.000" uom="g" recipe="R-48488" invFactor="1.0000" conversion="0.00100000" ingredient="P-26062"/>
	<Ingredient qty="2.000" uom="g" recipe="R-48488" invFactor="1.0000" conversion="1.00000000" ingredient="P-48495"/>
	<Ingredient qty="0.500" uom="CT" recipe="R-50312" invFactor="1.0000" conversion="1.00000000" ingredient="I-1196"/>
	<Ingredient qty="10.000" uom="g" recipe="R-50312" invFactor="1.0000" conversion="0.00220462" ingredient="I-4488"/>
	<Ingredient qty="15.000" uom="ml" recipe="R-50312" invFactor="1.0000" conversion="0.00100000" ingredient="P-34892"/>
	<Ingredient qty="30.000" uom="ml" recipe="R-50312" invFactor="1.0000" conversion="0.00100000" ingredient="P-36090"/>
	<Ingredient qty="1.000" uom="each" recipe="R-50312" invFactor="1.0000" conversion="1.00000000" ingredient="P-37297"/>
	<Ingredient qty="1.000" uom="each" recipe="R-50312" invFactor="1.0000" conversion="1.00000000" ingredient="P-44506"/>
	<Ingredient qty="2.000" uom="CT" recipe="R-50569" invFactor="1.0000" conversion="1.00000000" ingredient="I-2586"/>
	<Ingredient qty="40.000" uom="g" recipe="R-50569" invFactor="1.0000" conversion="1.00000000" ingredient="I-2899"/>
	<Ingredient qty="40.000" uom="ml" recipe="R-50569" invFactor="1.0000" conversion="0.00100000" ingredient="P-32739"/>
	<Ingredient qty="60.000" uom="g" recipe="R-50569" invFactor="1.0000" conversion="1.00000000" ingredient="P-50636"/>
	<Ingredient qty="2.000" uom="CT" recipe="R-50570" invFactor="1.0000" conversion="1.00000000" ingredient="I-2586"/>
	<Ingredient qty="40.000" uom="ml" recipe="R-50570" invFactor="1.0000" conversion="0.00100000" ingredient="P-32739"/>
	<Ingredient qty="65.000" uom="ml" recipe="R-50570" invFactor="1.0000" conversion="0.00100000" ingredient="P-50337"/>
	<Ingredient qty="2.000" uom="slice" recipe="R-51146" invFactor="1.0000" conversion="1.00000000" ingredient="I-17618"/>
	<Ingredient qty="1.000" uom="slice" recipe="R-51146" invFactor="1.0000" conversion="1.00000000" ingredient="I-2306"/>
	<Ingredient qty="1.000" uom="CT" recipe="R-51146" invFactor="1.0000" conversion="1.00000000" ingredient="I-2586"/>
	<Ingredient qty="5.000" uom="ml" recipe="R-51146" invFactor="1.0000" conversion="0.00100000" ingredient="I-3365"/>
	<Ingredient qty="20.000" uom="g" recipe="R-51146" invFactor="1.0000" conversion="0.00100000" ingredient="P-26205"/>
	<Ingredient qty="20.000" uom="g" recipe="R-51215" invFactor="1.0000" conversion="0.00100000" ingredient="P-26140"/>
	<Ingredient qty="120.000" uom="g" recipe="R-51215" invFactor="1.0000" conversion="0.00100000" ingredient="P-41573"/>
	<Ingredient qty="120.000" uom="g" recipe="R-51215" invFactor="1.0000" conversion="0.00100000" ingredient="P-44335"/>
	<Ingredient qty="1.000" uom="each" recipe="R-51215" invFactor="1.0000" conversion="1.00000000" ingredient="P-44392"/>
	<Ingredient qty="20.000" uom="g" recipe="R-51215" invFactor="1.0000" conversion="0.00100000" ingredient="P-46546"/>
	<Ingredient qty="10.000" uom="g" recipe="R-51215" invFactor="1.0000" conversion="0.00100000" ingredient="P-46911"/>
	<Ingredient qty="75.000" uom="g" recipe="R-51215" invFactor="1.0000" conversion="0.00100000" ingredient="P-56398"/>
	<Ingredient qty="0.750" uom="ea" recipe="R-51383" invFactor="1.0000" conversion="1.00000000" ingredient="I-27407"/>
	<Ingredient qty="75.000" uom="g" recipe="R-51383" invFactor="1.0000" conversion="0.00100000" ingredient="P-26055"/>
	<Ingredient qty="0.750" uom="ea" recipe="R-51383" invFactor="1.0000" conversion="1.00000000" ingredient="P-26057"/>
	<Ingredient qty="250.000" uom="g" recipe="R-51383" invFactor="1.0000" conversion="0.00100000" ingredient="P-44643"/>
	<Ingredient qty="10.000" uom="g" recipe="R-51383" invFactor="1.0000" conversion="1.00000000" ingredient="P-49552"/>
	<Ingredient qty="1.000" uom="each" recipe="R-51383" invFactor="1.0000" conversion="1.00000000" ingredient="P-51382"/>
	<Ingredient qty="10.000" uom="g" recipe="R-51383" invFactor="1.0000" conversion="0.00100000" ingredient="P-61821"/>
	<Ingredient qty="0.250" uom="ea" recipe="R-51383" invFactor="1.0000" conversion="1.00000000" ingredient="R-62249"/>
	<Ingredient qty="45.000" uom="ml" recipe="R-54377" invFactor="1.0000" conversion="0.00100000" ingredient="I-60772"/>
	<Ingredient qty="4.000" uom="slice" recipe="R-54377" invFactor="1.0000" conversion="1.00000000" ingredient="P-46862"/>
	<Ingredient qty="15.000" uom="g" recipe="R-54377" invFactor="1.0000" conversion="0.00220462" ingredient="P-50695"/>
	<Ingredient qty="1.000" uom="ea" recipe="R-54377" invFactor="1.0000" conversion="1.00000000" ingredient="P-50725"/>
	<Ingredient qty="4.000" uom="slice" recipe="R-54377" invFactor="1.0000" conversion="1.00000000" ingredient="P-51508"/>
	<Ingredient qty="30.000" uom="ml" recipe="R-54846" invFactor="1.0000" conversion="0.00100000" ingredient="P-34892"/>
	<Ingredient qty="1.000" uom="each" recipe="R-54846" invFactor="1.0000" conversion="1.00000000" ingredient="P-44392"/>
	<Ingredient qty="0.500" uom="CT" recipe="R-54846" invFactor="1.0000" conversion="1.00000000" ingredient="P-51086"/>
	<Ingredient qty="30.000" uom="g" recipe="R-54846" invFactor="1.0000" conversion="0.00100000" ingredient="P-8205"/>
	<Ingredient qty="4.000" uom="g" recipe="R-54846" invFactor="1.0000" conversion="0.00100000" ingredient="P-9741"/>
	<Ingredient qty="250.000" uom="g" recipe="R-61822" invFactor="1.0000" conversion="0.00100000" ingredient="P-44643"/>
	<Ingredient qty="25.000" uom="g" recipe="R-61844" invFactor="1.0000" conversion="0.00100000" ingredient="P-26062"/>
	<Ingredient qty="2.000" uom="g" recipe="R-61844" invFactor="1.0000" conversion="1.00000000" ingredient="P-26514"/>
	<Ingredient qty="60.000" uom="g" recipe="R-61844" invFactor="1.0000" conversion="0.00100000" ingredient="P-52042"/>
	<Ingredient qty="30.000" uom="g" recipe="R-61844" invFactor="1.0000" conversion="0.00100000" ingredient="P-56398"/>
	<Ingredient qty="120.000" uom="g" recipe="R-61844" invFactor="1.0000" conversion="0.00100000" ingredient="P-61843"/>
	<Ingredient qty="5.000" uom="g" recipe="R-61859" invFactor="1.0000" conversion="0.03527399" ingredient="P-34534"/>
	<Ingredient qty="2.000" uom="each" recipe="R-61859" invFactor="1.0000" conversion="1.00000000" ingredient="P-44392"/>
	<Ingredient qty="20.000" uom="g" recipe="R-61859" invFactor="1.0000" conversion="0.00100000" ingredient="P-50231"/>
	<Ingredient qty="25.000" uom="g" recipe="R-61859" invFactor="1.0000" conversion="0.00100000" ingredient="P-50543"/>
	<Ingredient qty="35.000" uom="ml" recipe="R-61859" invFactor="1.0000" conversion="0.00100000" ingredient="P-50744"/>
	<Ingredient qty="180.000" uom="g" recipe="R-61859" invFactor="1.0000" conversion="0.00100000" ingredient="P-6975"/>
	<Ingredient qty="25.000" uom="g" recipe="R-61859" invFactor="1.0000" conversion="0.00100000" ingredient="P-9857"/>
	<Ingredient qty="1.000" uom="CT" recipe="R-62001" invFactor="1.0000" conversion="1.00000000" ingredient="I-1197"/>
	<Ingredient qty="60.000" uom="ml" recipe="R-62001" invFactor="1.0000" conversion="0.00100000" ingredient="P-34892"/>
	<Ingredient qty="2.000" uom="each" recipe="R-62001" invFactor="1.0000" conversion="1.00000000" ingredient="P-44392"/>
	<Ingredient qty="1.000" uom="CT" recipe="R-62002" invFactor="1.0000" conversion="1.00000000" ingredient="I-1197"/>
	<Ingredient qty="50.000" uom="ml" recipe="R-62002" invFactor="1.0000" conversion="0.00100000" ingredient="P-34892"/>
	<Ingredient qty="2.000" uom="each" recipe="R-62002" invFactor="1.0000" conversion="1.00000000" ingredient="P-44392"/>
	<Ingredient qty="30.000" uom="g" recipe="R-62002" invFactor="1.0000" conversion="0.00100000" ingredient="P-50231"/>
	<Ingredient qty="20.000" uom="ml" recipe="R-62002" invFactor="1.0000" conversion="0.00100000" ingredient="P-50744"/>
	<Ingredient qty="1.000" uom="CT" recipe="R-62012" invFactor="1.0000" conversion="1.00000000" ingredient="I-1197"/>
	<Ingredient qty="50.000" uom="ml" recipe="R-62012" invFactor="1.0000" conversion="0.00100000" ingredient="P-34892"/>
	<Ingredient qty="2.000" uom="each" recipe="R-62012" invFactor="1.0000" conversion="1.00000000" ingredient="P-44392"/>
	<Ingredient qty="30.000" uom="ml" recipe="R-62012" invFactor="1.0000" conversion="0.00100000" ingredient="P-56455"/>
	<Ingredient qty="75.000" uom="g" recipe="R-62012" invFactor="1.0000" conversion="0.00100000" ingredient="P-61821"/>
	<Ingredient qty="4.000" uom="g" recipe="R-62012" invFactor="1.0000" conversion="0.00100000" ingredient="P-9741"/>
	<Ingredient qty="60.000" uom="g" recipe="R-62249" invFactor="1.0000" conversion="0.00100000" ingredient="P-44737"/>
	<Ingredient qty="225.000" uom="g" recipe="R-62379" invFactor="1.0000" conversion="0.00100000" ingredient="P-58403"/>
	<Ingredient qty="1.000" uom="ea" recipe="R-65755" invFactor="1.0000" conversion="1.00000000" ingredient="I-64877"/>
	<Ingredient qty="75.000" uom="g" recipe="R-65755" invFactor="1.0000" conversion="0.00100000" ingredient="P-26055"/>
	<Ingredient qty="20.000" uom="g" recipe="R-65755" invFactor="1.0000" conversion="1.00000000" ingredient="P-26069"/>
	<Ingredient qty="50.000" uom="g" recipe="R-65755" invFactor="1.0000" conversion="0.00100000" ingredient="P-26075"/>
	<Ingredient qty="50.000" uom="ml" recipe="R-65755" invFactor="1.0000" conversion="0.00100000" ingredient="P-36090"/>
	<Ingredient qty="1.000" uom="CT" recipe="R-65755" invFactor="1.0000" conversion="1.00000000" ingredient="P-51086"/>
	<Ingredient qty="1.000" uom="slice" recipe="R-67745" invFactor="1.0000" conversion="1.00000000" ingredient="I-17618"/>
	<Ingredient qty="2.000" uom="CT" recipe="R-67745" invFactor="1.0000" conversion="1.00000000" ingredient="I-2586"/>
	<Ingredient qty="40.000" uom="g" recipe="R-67745" invFactor="1.0000" conversion="0.00100000" ingredient="P-26205"/>
	<Ingredient qty="45.000" uom="ml" recipe="R-68099" invFactor="1.0000" conversion="0.00100000" ingredient="I-3670"/>
	<Ingredient qty="2.000" uom="each" recipe="R-68099" invFactor="1.0000" conversion="1.00000000" ingredient="P-50505"/>
	<Ingredient qty="60.000" uom="ml" recipe="R-68099" invFactor="1.0000" conversion="0.00100000" ingredient="P-58949"/>
	<Ingredient qty="35.000" uom="ml" recipe="R-68107" invFactor="1.0000" conversion="0.00100000" ingredient="P-35251"/>
	<Ingredient qty="50.000" uom="g" recipe="R-68107" invFactor="1.0000" conversion="0.00100000" ingredient="P-44335"/>
	<Ingredient qty="1.000" uom="each" recipe="R-68107" invFactor="1.0000" conversion="1.00000000" ingredient="P-44392"/>
	<Ingredient qty="50.000" uom="g" recipe="R-68107" invFactor="1.0000" conversion="0.00100000" ingredient="P-44913"/>
	<Ingredient qty="175.000" uom="g" recipe="R-68107" invFactor="1.0000" conversion="0.00100000" ingredient="P-50287"/>
	<Ingredient qty="10.000" uom="g" recipe="R-68107" invFactor="1.0000" conversion="1.00000000" ingredient="P-50853"/>
	<Ingredient qty="30.000" uom="g" recipe="R-68107" invFactor="1.0000" conversion="0.00100000" ingredient="P-50966"/>
	<Ingredient qty="5.000" uom="g" recipe="R-68107" invFactor="1.0000" conversion="1.00000000" ingredient="P-52943"/>
	<Ingredient qty="20.000" uom="g" recipe="R-68107" invFactor="1.0000" conversion="0.00100000" ingredient="P-56778"/>
	<Ingredient qty="45.000" uom="ml" recipe="R-68108" invFactor="1.0000" conversion="0.00100000" ingredient="I-3670"/>
	<Ingredient qty="1.000" uom="each" recipe="R-68108" invFactor="1.0000" conversion="1.00000000" ingredient="P-50505"/>
	<Ingredient qty="60.000" uom="ml" recipe="R-68108" invFactor="1.0000" conversion="0.00100000" ingredient="P-50739"/>
	<Ingredient qty="1.000" uom="CT" recipe="R-68109" invFactor="1.0000" conversion="1.00000000" ingredient="I-1196"/>
	<Ingredient qty="60.000" uom="ml" recipe="R-68109" invFactor="1.0000" conversion="0.00100000" ingredient="P-34892"/>
	<Ingredient qty="2.000" uom="each" recipe="R-68109" invFactor="1.0000" conversion="1.00000000" ingredient="P-44392"/>
	<Ingredient qty="40.000" uom="g" recipe="R-68109" invFactor="1.0000" conversion="0.00100000" ingredient="P-65937"/>
	<Ingredient qty="4.000" uom="g" recipe="R-68109" invFactor="1.0000" conversion="0.00100000" ingredient="P-9741"/>
	<Ingredient qty="1.000" uom="CT" recipe="R-68110" invFactor="1.0000" conversion="1.00000000" ingredient="I-1197"/>
	<Ingredient qty="50.000" uom="ml" recipe="R-68110" invFactor="1.0000" conversion="0.00100000" ingredient="P-34892"/>
	<Ingredient qty="2.000" uom="each" recipe="R-68110" invFactor="1.0000" conversion="1.00000000" ingredient="P-44392"/>
	<Ingredient qty="20.000" uom="ml" recipe="R-68110" invFactor="1.0000" conversion="0.00100000" ingredient="P-50744"/>
	<Ingredient qty="30.000" uom="g" recipe="R-68110" invFactor="1.0000" conversion="0.00100000" ingredient="P-51242"/>
	<Ingredient qty="0.150" uom="LOAF" recipe="R-68973" invFactor="1.0000" conversion="1.00000000" ingredient="I-15032"/>
	<Ingredient qty="40.000" uom="g" recipe="R-68973" invFactor="1.0000" conversion="0.00100000" ingredient="I-2156"/>
	<Ingredient qty="1.000" uom="g" recipe="R-68973" invFactor="1.0000" conversion="1.00000000" ingredient="I-3625"/>
	<Ingredient qty="10.000" uom="g" recipe="R-68973" invFactor="1.0000" conversion="1.00000000" ingredient="I-8060"/>
	<Ingredient qty="30.000" uom="g" recipe="R-68973" invFactor="1.0000" conversion="0.00100000" ingredient="P-68106"/>
	<Ingredient qty="0.150" uom="LOAF" recipe="R-69126" invFactor="1.0000" conversion="1.00000000" ingredient="I-15032"/>
	<Ingredient qty="40.000" uom="g" recipe="R-69126" invFactor="1.0000" conversion="0.00100000" ingredient="I-2156"/>
	<Ingredient qty="1.000" uom="g" recipe="R-69126" invFactor="1.0000" conversion="1.00000000" ingredient="I-3625"/>
	<Ingredient qty="10.000" uom="g" recipe="R-69126" invFactor="1.0000" conversion="1.00000000" ingredient="I-8060"/>
	<Ingredient qty="30.000" uom="g" recipe="R-69126" invFactor="1.0000" conversion="0.00100000" ingredient="P-64884"/>
</Ingredients>
